tagged/__init__.py
tagged-0.0.2.dist-info/LICENSE
tagged-0.0.2.dist-info/METADATA
tagged-0.0.2.dist-info/WHEEL
tagged-0.0.2.dist-info/top_level.txt
tagged-0.0.2.dist-info/RECORD
