Metadata-Version: 2.1
Name: tagged
Version: 0.0.2
Summary: Tagged templates for Python
Home-page: https://github.com/jviide/tagged
Author: Joachim Viide
Author-email: jviide@iki.fi
License: UNKNOWN
Platform: UNKNOWN
Classifier: Programming Language :: Python :: 3
Classifier: License :: OSI Approved :: MIT License
Classifier: Operating System :: OS Independent
